ecowater_softener/__init__.py
ecowater_softener/const.py
ecowater_softener/ecowater.py
ecowater_softener_test-2.2.2.dist-info/LICENSE
ecowater_softener_test-2.2.2.dist-info/METADATA
ecowater_softener_test-2.2.2.dist-info/WHEEL
ecowater_softener_test-2.2.2.dist-info/top_level.txt
ecowater_softener_test-2.2.2.dist-info/RECORD
