Metadata-Version: 2.1
Name: ecowater-softener-test
Version: 2.2.2
Summary: This a forked version only for testing purposes. The original code is property of barleybobs, you can find it at ecowater-softener. A small package to pull data from Ecowater water softeners
Home-page: https://github.com/figorr/ecowater-softener
Author: figorr
Classifier: Programming Language :: Python :: 3
Classifier: License :: OSI Approved :: MIT License
Classifier: Operating System :: OS Independent
License-File: LICENSE
Requires-Dist: ayla-iot-unofficial ==1.4.1
